pickle_function_cache.py
pickle_function_cache-0.1.5.dist-info/LICENSE.txt
pickle_function_cache-0.1.5.dist-info/METADATA
pickle_function_cache-0.1.5.dist-info/WHEEL
pickle_function_cache-0.1.5.dist-info/top_level.txt
pickle_function_cache-0.1.5.dist-info/RECORD
