Metadata-Version: 2.1
Name: pickle-function-cache
Version: 0.1.5
Summary: Caching of the function results in a file.
Home-page: https://gitlab.com/oleksandr.zelentsov/pickle-function-cache
Author: Oleksandr Zelentsov
Author-email: oleksandrzelentsov@gmail.com
License: LICENSE.txt
License-File: LICENSE.txt
